{
  "$schema": "https://mintlify.com/docs.json",
  "theme": "mint",
  "name": "Kisuke",
  "colors": {
    "primary": "#a7c080",
    "light": "#83c092",
    "dark": "#7fbbb3"
  },
  "modeToggle": {
    "default": "dark",
    "isHidden": true
  },
  "favicon": "/favicon.svg",
  "navigation": {
    "tabs": [
      {
        "tab": "Documentation",
        "groups": [
          {
            "group": "Getting Started",
            "pages": [
              "introduction",
              "what-is-kisuke"
            ]
          },
          {
            "group": "Installation",
            "pages": [
              "installation/overview",
              "installation/mobile",
              "installation/mac",
              "installation/windows",
              "installation/linux",
              "installation/cli-docker"
            ]
          },
          {
            "group": "Core Concepts",
            "pages": [
              "concepts/kisuke-connect",
              "concepts/relay-system",
              "concepts/security"
            ]
          },
          {
            "group": "Core Features",
            "pages": [
              "features/terminal",
              "features/spaces",
              "features/coding-with-ai",
              "features/editor",
              "features/browser"
            ]
          },
          {
            "group": "Advanced Configuration",
            "pages": [
              "advanced/self-hosting",
              "advanced/custom-infra",
              "advanced/admin-console"
            ]
          }
        ]
      }
    ],
    "global": {
      "anchors": [
        {
          "anchor": "Download",
          "href": "https://kisuke.app",
          "icon": "download"
        },
        {
          "anchor": "GitHub",
          "href": "https://github.com/kisuke-app",
          "icon": "github"
        }
      ]
    }
  },
  "logo": {
    "light": "/logo/light.svg",
    "dark": "/logo/dark.svg"
  },
  "navbar": {
    "links": [
      {
        "label": "Support",
        "href": "mailto:support@kisuke.app"
      }
    ],
    "primary": {
      "type": "button",
      "label": "Download",
      "href": "https://kisuke.app"
    }
  },
  "footer": {
    "socials": {
      "x": "https://x.com/kisuke_app",
      "github": "https://github.com/kisuke-app"
    }
  }
}
